models_dev/__init__.py
models_dev/_loader.py
models_dev/_types.py
models_dev/data.json.gz
models_dev/py.typed
models_dev-1.0.54.dist-info/METADATA
models_dev-1.0.54.dist-info/WHEEL
models_dev-1.0.54.dist-info/licenses/LICENSE
models_dev-1.0.54.dist-info/RECORD
